crystalpayapi/__init__.py
crystalpayapi/api.py
crystalpayapi-1.2.0.dist-info/licenses/LICENSE
crystalpayapi-1.2.0.dist-info/METADATA
crystalpayapi-1.2.0.dist-info/WHEEL
crystalpayapi-1.2.0.dist-info/top_level.txt
crystalpayapi-1.2.0.dist-info/RECORD
